coreason_etl_drugs_fda/__init__.py
coreason_etl_drugs_fda/gold.py
coreason_etl_drugs_fda/pipeline.py
coreason_etl_drugs_fda/silver.py
coreason_etl_drugs_fda/source.py
coreason_etl_drugs_fda/transform.py
coreason_etl_drugs_fda/utils/__init__.py
coreason_etl_drugs_fda/utils/logger.py
coreason_etl_drugs_fda/utils/medallion.py
coreason_etl_drugs_fda-0.2.0.dist-info/METADATA
coreason_etl_drugs_fda-0.2.0.dist-info/WHEEL
coreason_etl_drugs_fda-0.2.0.dist-info/licenses/LICENSE
coreason_etl_drugs_fda-0.2.0.dist-info/licenses/NOTICE
coreason_etl_drugs_fda-0.2.0.dist-info/RECORD
