Metadata-Version: 2.4
Name: coreason_etl_drugs_fda
Version: 0.2.0
Summary: Fast, extensible Python ETL to maintain a local Drugs FDA mirror
License: # The Prosperity Public License 3.0.0
License-File: LICENSE
License-File: NOTICE
Author: Gowtham A Rao
Author-email: gowtham.rao@coreason.ai
Requires-Python: >=3.11
Classifier: License :: Other/Proprietary License
Classifier: Programming Language :: Python :: 3.12
Classifier: Operating System :: OS Independent
Requires-Dist: curl-cffi (>=0.14.0,<0.15.0)
Requires-Dist: dlt (>=1.20.0,<2.0.0)
Requires-Dist: loguru (>=0.7.3,<0.8.0)
Requires-Dist: polars (>=1.36.1,<2.0.0)
Requires-Dist: pydantic (>=2.12.5,<3.0.0)
Requires-Dist: setuptools (>=80.9.0,<81.0.0)
Project-URL: Documentation, https://github.com/CoReason-AI/coreason_etl_drugs_fda
Project-URL: Homepage, https://github.com/CoReason-AI/coreason_etl_drugs_fda
Project-URL: Repository, https://github.com/CoReason-AI/coreason_etl_drugs_fda
